sc.recipe.staticresources-1.1b2-py2.7-nspkg.pth
sc/recipe/staticresources/__init__.py
sc/recipe/staticresources/__init__.pyc
sc/recipe/staticresources/bobtemplate/.gitignore
sc/recipe/staticresources/bobtemplate/karma.conf.js
sc/recipe/staticresources/bobtemplate/package.json.bob
sc/recipe/staticresources/bobtemplate/postcss.config.js
sc/recipe/staticresources/bobtemplate/webpack.config.js.bob
sc/recipe/staticresources/bobtemplate/app/+short_name+.js
sc/recipe/staticresources/bobtemplate/app/+short_name+.scss
sc/recipe/staticresources/bobtemplate/app/index.html
sc/recipe/staticresources/bobtemplate/app/resources.pt
sc/recipe/staticresources/bobtemplate/app/js/filea.js
sc/recipe/staticresources/bobtemplate/app/scss/_sprite.scss
sc/recipe/staticresources/bobtemplate/tests/+short_name+.spec.js.bob
sc/recipe/staticresources/bobtemplate/tests/filea.spec.js
sc/recipe/staticresources/tests/__init__.py
sc/recipe/staticresources/tests/__init__.pyc
sc/recipe/staticresources/tests/test_recipe.py
sc/recipe/staticresources/tests/test_recipe.pyc
sc.recipe.staticresources-1.1b2.dist-info/METADATA
sc.recipe.staticresources-1.1b2.dist-info/RECORD
sc.recipe.staticresources-1.1b2.dist-info/WHEEL
sc.recipe.staticresources-1.1b2.dist-info/entry_points.txt
sc.recipe.staticresources-1.1b2.dist-info/namespace_packages.txt
sc.recipe.staticresources-1.1b2.dist-info/top_level.txt
