Metadata-Version: 2.1
Name: sc.recipe.staticresources
Version: 1.1b2
Summary: FIXME
Home-page: http://github.com/simplesconsultoria/sc.recipe.staticresources/
Author: Simples Consultoria
Author-email: products@simplesconsultoria.com.br
License: UNKNOWN
Platform: UNKNOWN
Classifier: Development Status :: 3 - Alpha
Classifier: Framework :: Buildout
Classifier: Intended Audience :: Developers
Classifier: License :: OSI Approved :: GNU General Public License v2 (GPLv2)
Classifier: Operating System :: OS Independent
Classifier: Programming Language :: Python :: 2.7
Classifier: Programming Language :: Python
Classifier: Topic :: Software Development :: Build Tools
Provides-Extra: test
Requires-Dist: mr.bob
Requires-Dist: setuptools
Requires-Dist: zc.buildout
Requires-Dist: zc.recipe.egg
Provides-Extra: test
Requires-Dist: testfixtures; extra == 'test'
Requires-Dist: zc.buildout[test]; extra == 'test'
Requires-Dist: zope.testing; extra == 'test'
